threads_dlp/__init__.py
threads_dlp/database.py
threads_dlp/downloader.py
threads_dlp/languages.json
threads_dlp/main.py
threads_dlp/scraper.py
threads_dlp/threads_client.py
threads_dlp/uploader.py
threads_dlp_layorx-1.0.3.dist-info/METADATA
threads_dlp_layorx-1.0.3.dist-info/WHEEL
threads_dlp_layorx-1.0.3.dist-info/entry_points.txt
threads_dlp_layorx-1.0.3.dist-info/licenses/LICENSE
threads_dlp_layorx-1.0.3.dist-info/RECORD
