Metadata-Version: 2.4
Name: threads-dlp-layorx
Version: 1.0.3
Summary: A tool to download videos from Threads user pages.
Author-email: LayorX <your@email.com>
License-File: LICENSE
Classifier: License :: OSI Approved :: MIT License
Classifier: Operating System :: OS Independent
Classifier: Programming Language :: Python :: 3
Requires-Python: >=3.10
Requires-Dist: blinker==1.7.0
Requires-Dist: datasette-auth-passwords>=1.1.1
Requires-Dist: datasette>=0.65.1
Requires-Dist: google-generativeai>=0.8.5
Requires-Dist: honcho>=2.0.0
Requires-Dist: requests>=2.32.5
Requires-Dist: schedule>=1.2.2
Requires-Dist: selenium-wire>=5.1.0
Requires-Dist: selenium>=4.37.0
Requires-Dist: setuptools>=80.9.0
Requires-Dist: tabulate>=0.9.0
Requires-Dist: webdriver-manager>=4.0.2
Requires-Dist: yt-dlp>=2025.10.14
Requires-Dist: zstandard>=0.25.0
Requires-Dist: zstd>=1.5.7.2
